CURD.py
setup.py
CURD.py.egg-info/PKG-INFO
CURD.py.egg-info/SOURCES.txt
CURD.py.egg-info/dependency_links.txt
CURD.py.egg-info/top_level.txt