Metadata-Version: 1.1
Name: CURD.py
Version: 0.6.0
Summary: Tiny Python ORM for MySQL
Home-page: https://github.com/hit9/CURD.py
Author: hit9
Author-email: nz2324@126.com
License: BSD
Keywords: CURD ORM MySQL Python tiny database
Platform: UNKNOWN
Classifier: Development Status :: 4 - Beta
Classifier: Environment :: Web Environment
Classifier: Intended Audience :: Developers
Classifier: License :: OSI Approved :: BSD License
Classifier: Operating System :: OS Independent
Classifier: Programming Language :: Python
Classifier: Programming Language :: Python :: 3
Classifier: Topic :: Database
Classifier: Topic :: Software Development :: Libraries :: Python Modules
